{
	"format_version": "1.8.0",
	"animations": {
		"animation.umbrelligant.ground_idle": {
			"loop": true,
			"animation_length": 2,
			"bones": {
				"body": {
					"position": [0, 0, 0]
				},
				"torso": {
					"rotation": [5, 0, 0]
				},
				"waist": {
					"rotation": {
						"0.0": [-2.5, 5, 5],
						"1.0": [-5, -5, -5],
						"2.0": [-2.5, 5, 5]
					}
				},
				"chest": {
					"rotation": {
						"0.0": [-5, 0, -10],
						"1.0": [2.2047, 5.7671, 15.63053],
						"2.0": [-4.85095, -0.63174, -8.93845]
					}
				},
				"head": {
					"rotation": [5, -2.5, -5]
				},
				"leg_left": {
					"rotation": {
						"0.0": [-5, -15, -2.5],
						"1.0": [-5.13932, -19.98047, -2.03689],
						"2.0": [-5, -15, -2.5]
					}
				},
				"leg_right": {
					"rotation": {
						"0.0": [5, 15, 2.5],
						"1.0": [5.22705, 22.47025, 3.20537],
						"2.0": [5, 15, 2.5]
					}
				},
				"umbrelligant": {
					"scale": 1
				},
				"hair_back": {
					"rotation": {
						"0.0": [-5, 0, 7.5],
						"1.0": [7.73032, -1.50179, -9.93745],
						"2.0": [-5, 0, 7.5]
					}
				},
				"hat": {
					"rotation": {
						"0.0": [0, -17.5, 5],
						"1.0": [7.31883, 12.26069, 8.82943],
						"2.0": [0, -17.5, 5]
					}
				}
			}
		},
		"animation.umbrelligant.blink": {
			"animation_length": 0.2083,
			"bones": {
				"eye_left": {
					"position": {
						"0.0": [0, 0, 0],
						"0.125": [0, 0, 0],
						"0.2083": [0, 0, 0]
					},
					"scale": {
						"0.0": [1, 1, 1],
						"0.125": [1.4, 0, 1],
						"0.2083": [1, 1, 1]
					}
				},
				"eye_right": {
					"position": {
						"0.0": [0, 0, 0],
						"0.125": [0, 0, 0],
						"0.2083": [0, 0, 0]
					},
					"scale": {
						"0.0": [1, 1, 1],
						"0.125": [1.4, 0, 1],
						"0.2083": [1, 1, 1]
					}
				}
			}
		},
		"animation.umbrelligant.cry": {
			"animation_length": 1.75,
			"bones": {
				"torso": {
					"rotation": [5, 0, 0]
				},
				"waist": {
					"rotation": {
						"0.0": [-2.5, 5, 5],
						"0.25": [-15.60865, 4.30566, -2.49256],
						"0.3333": [-20.60865, 4.30566, -2.49256],
						"0.625": [16.50222, -6.60066, -10.37399],
						"1.0": [24.55319, -67.737, -22.77992],
						"1.25": [87.1029, -81.78533, -86.7758],
						"1.5417": [29.02514, -36.08993, -22.77893],
						"1.75": [-2.5, 5, 5]
					}
				},
				"chest": {
					"rotation": {
						"0.0": [-5, 0, -10],
						"0.25": [42.68542, 1.29956, -0.66745],
						"0.3333": [55.18542, 1.29956, -0.66745],
						"0.625": [-3.26354, 9.48396, 8.80045],
						"1.0": [0.96431, 76.6132, -4.33007],
						"1.25": [117.76639, 75.68376, 111.78569],
						"1.75": [-5, 0, -10]
					}
				},
				"head": {
					"rotation": {
						"0.0": [5, -2.5, -5],
						"0.25": [22.30335, -7.90839, -0.43126],
						"0.3333": [25.66382, -17.13526, -4.38565],
						"0.625": [-16.0199, -3.22547, 10.36581],
						"1.0": [-9.37018, -7.84629, -6.59752],
						"1.25": [-9.42553, -2.55306, -22.54195],
						"1.75": [5, -2.5, -5]
					}
				},
				"hair_back": {
					"rotation": {
						"0.0": [-5, 0, 7.5],
						"0.25": [-40, 0, 7.5],
						"0.3333": [-52.5, 0, 7.5],
						"0.625": [31.67056, 2.42686, -5.7313],
						"1.0": [18.83185, -5.4436, 7.05257],
						"1.25": [23.31325, -7.03705, 11.82028],
						"1.75": [-5, 0, 7.5]
					},
					"position": {
						"0.0": [0, 0, 0],
						"0.25": [0, -2.5, 2],
						"0.3333": [0, -3, 2.75],
						"0.625": [0, -1.5, -2.25],
						"1.0": [-0.5, -1.5, -1.5],
						"1.75": [0, 0, 0]
					}
				},
				"hat": {
					"rotation": {
						"0.0": [0, -17.5, 5],
						"0.25": [3.89065, -39.68504, -7.03259],
						"0.3333": [15.35034, -53.29611, -21.33362],
						"0.625": [-45.91516, -81.87966, 38.18887],
						"0.8333": [-7.07884, -33.79083, 1.22116],
						"1.0": [-4.89956, 14.04226, 1.35601],
						"1.25": [-40.49255, 86.09437, -32.73863],
						"1.75": [0, -17.5, 5]
					},
					"position": {
						"0.0": [0, 0, 0],
						"0.3333": [0, 0, -2],
						"0.625": [0, 0, -1],
						"1.0": [-0.75, 0, 0],
						"1.75": [0, 0, 0]
					}
				},
				"leg_left": {
					"rotation": {
						"0.0": [-5, -15, -2.5],
						"0.25": [-2.41476, -0.01363, -3.14686],
						"0.3333": [0.08524, -0.01363, -3.14686],
						"0.625": [24.45325, -22.03915, -15.53207],
						"1.0": [26.95325, -22.03915, -15.53207],
						"1.25": [27.82616, -20.88887, -17.91721],
						"1.75": [-5, -15, -2.5]
					}
				},
				"leg_right": {
					"rotation": {
						"0.0": [5, 15, 2.5],
						"0.25": [2.43565, 7.50693, 2.17097],
						"0.3333": [-0.06435, 7.50693, 2.17097],
						"0.625": [-9.57414, 15.58064, 6.24745],
						"1.0": [-12.07414, 15.58064, 6.24745],
						"1.25": [-12.74275, 15.04335, 3.71598],
						"1.75": [5, 15, 2.5]
					},
					"position": {
						"0.0": [0, 0, 0],
						"0.625": [0.75, 0, 0.5],
						"1.75": [0, 0, 0]
					}
				}
			},
			"sound_effects": {
				"0.0417": {
					"effect": "pokemon.lilligant_hisuian.cry"
				}
			}
		},
		"animation.umbrelligant.ground_walk": {
			"loop": true,
			"animation_length": 1,
			"bones": {
				"body": {
					"position": {
						"0.0": [0, 0, 0],
						"0.25": [0, 1.5, 0],
						"0.5": [0, 0, 0],
						"0.75": [0, 1.5, 0],
						"1.0": [0, 0, 0]
					}
				},
				"waist": {
					"rotation": {
						"0.0": [0, 0, 0],
						"0.25": [7.5, 0, 12.5],
						"0.5": [0, 0, 0],
						"0.75": [8.62852, -12.34608, -17.34653],
						"1.0": [0, 0, 0]
					},
					"scale": {
						"0.0": [1, 1, 1],
						"0.25": [1.1, 0.9, 1.1],
						"0.5": [1, 1, 1],
						"0.75": [1.1, 0.9, 1.1],
						"1.0": [1, 1, 1]
					}
				},
				"chest": {
					"rotation": {
						"0.0": [5, 0, 0],
						"0.25": [-1.30962, 7.38542, -10.08453],
						"0.5": [5, 0, 0],
						"0.75": [6.61079, -5.70652, 6.70978],
						"1.0": [5, 0, 0]
					},
					"scale": {
						"0.0": [1, 1, 1],
						"0.25": [0.9, 1.1, 0.9],
						"0.5": [1, 1, 1],
						"0.75": [0.9, 1.1, 0.9],
						"1.0": [1, 1, 1]
					}
				},
				"head": {
					"rotation": {
						"0.0": [7.5, 0, 0],
						"0.25": [2.74715, -12.19908, -12.79362],
						"0.5": [7.5, 0, 0],
						"0.75": [-4.96527, 18.0124, 9.83856],
						"1.0": [7.5, 0, 0]
					}
				},
				"hair_back": {
					"rotation": {
						"0.0": [-10, 0, 0],
						"0.25": [14.07749, -9.13624, 30.3808],
						"0.5": [-10, 0, 0],
						"0.75": [7.67367, 20.10841, -22.63561],
						"1.0": [-10, 0, 0]
					},
					"position": {
						"0.0": [0, 0, 0],
						"0.25": [0, 0, -0.75],
						"0.5": [0, 0, 0],
						"0.75": [0, 0, -1],
						"1.0": [0, 0, 0]
					}
				},
				"hat": {
					"rotation": {
						"0.0": [0, 0, 0],
						"0.25": [-7.92077, 21.12432, 7.21402],
						"0.5": [0, 0, 0],
						"0.75": [9.13039, -34.65749, -15.22206],
						"1.0": [0, 0, 0]
					},
					"position": {
						"0.0": [0, 0, 0],
						"0.25": [0.17, -0.5, -0.33],
						"0.5": [0, 0, 0],
						"0.75": [-1, 0, -1],
						"1.0": [0, 0, 0]
					}
				},
				"leg_left": {
					"rotation": {
						"0.0": [2.6089, -2.38613, -2.6089],
						"0.25": [42.16569, 4.20854, -9.07947],
						"0.5": [-2.3911, -2.38613, -2.6089],
						"0.75": [-39.20555, -7.10256, -11.38656],
						"1.0": [2.6089, -2.38613, -2.6089]
					},
					"position": {
						"0.0": [0, 0, 0],
						"0.25": [-1, 0, 0],
						"0.5": [0, 0, 0],
						"1.0": [0, 0, 0]
					}
				},
				"leg_right": {
					"rotation": {
						"0.0": [-2.72622, 5.09907, 2.26982],
						"0.25": [-34.69157, 3.81024, 9.25249],
						"0.5": [4.77378, 5.09907, 2.26982],
						"0.75": [35.13002, -0.27659, 10.71264],
						"1.0": [-2.72622, 5.09907, 2.26982]
					}
				}
			}
		},
		"animation.umbrelligant.sleep": {
			"loop": true,
			"animation_length": 2,
			"bones": {
				"body": {
					"position": [0, -13.5, 0]
				},
				"waist": {
					"rotation": {
						"0.0": [-5, 0, 0],
						"1.0": [-7.5, 0, 0],
						"2.0": [-5, 0, 0]
					},
					"position": [0, 7, 0],
					"scale": [1.1, 0.9, 1.1]
				},
				"chest": {
					"rotation": {
						"0.0": [35, 0, 0],
						"1.0": [27.5, 0, 0],
						"2.0": [35, 0, 0]
					},
					"position": [0, -0.5, 0],
					"scale": [0.8, 0.9, 1.2]
				},
				"head": {
					"rotation": {
						"0.0": [10.34527, 14.76689, -14.83601],
						"1.0": [5.93409, 12.03337, -12.53162],
						"2.0": [10.34527, 14.76689, -14.83601]
					}
				},
				"eye_left": {
					"scale": [1.4, 0.2, 1]
				},
				"eye_right": {
					"scale": [1.4, 0.2, 1]
				},
				"hair_back": {
					"rotation": {
						"0.0": [-32.5, 0, 15],
						"1.0": [-32.59907, -4.21541, 17.69136],
						"2.0": [-32.5, 0, 15]
					},
					"position": {
						"0.0": [0, -2, 1.75],
						"1.0": [-0.5, -1.5, 2],
						"2.0": [0, -2, 1.75]
					}
				},
				"hat": {
					"rotation": {
						"0.0": [5, 0, 7.5],
						"1.0": [12.45392, 1.08089, 2.61794],
						"2.0": [5, 0, 7.5]
					},
					"position": {
						"0.0": [0, 0, 0],
						"1.0": [0, 0, -0.75],
						"2.0": [0, 0, 0]
					},
					"scale": [1.1, 1, 0.9]
				},
				"leg_left": {
					"rotation": [-90, -17.5, 0]
				},
				"leg_right": {
					"rotation": [-90, 17.5, 0]
				}
			}
		},
		"animation.umbrelligant.faint": {
			"animation_length": 3,
			"bones": {
				"body": {
					"rotation": {
						"0.0": [0, 0, 0],
						"0.75": [0, 0, 0],
						"1.0": [45, 0, 0],
						"1.5": [47.5, 0, 0]
					},
					"position": {
						"0.0": [0, 0, 0],
						"0.2917": [0, 0, 5],
						"0.75": [0, 0, -5],
						"1.0": [0, 0, -9],
						"1.25": [0, -1, -9],
						"1.5": [0, -8, -9]
					}
				},
				"waist": {
					"rotation": {
						"0.0": [-2.5, 0, 0],
						"0.25": [-20, 0, 0],
						"0.75": [10, 0, 0],
						"1.0": [-10, 0, 0],
						"1.5": [65, 0, 0],
						"2.0": [25, 0, 0]
					},
					"position": {
						"0.0": [0, 0, 0],
						"1.5": [0, -2, -7]
					}
				},
				"chest": {
					"rotation": {
						"0.0": [10, 0, 0],
						"0.25": [-7.5, 0, 0],
						"0.75": [-12.5, 0, 0],
						"1.0": [-27.5, 0, 0],
						"2.0": [-2.5, 0, 0]
					}
				},
				"head": {
					"rotation": {
						"0.0": [15, 0, 0],
						"0.25": [-17.5, 0, 0],
						"0.75": [-22.5, 0, 0],
						"1.0": [-21.80633, 5.68422, 13.9042],
						"1.5": [-11.24758, 19.13225, 13.95419],
						"2.0": [13.6594, 2.00871, 4.56749]
					}
				},
				"eye_left": {
					"rotation": {
						"0.0": [0, 0, 0],
						"0.125": [0, 0, 0],
						"0.25": [0, 0, -27.5]
					},
					"scale": {
						"0.0": [1, 1, 1],
						"0.25": [1.4, 0.2, 1]
					}
				},
				"eye_right": {
					"rotation": {
						"0.0": [0, 0, 0],
						"0.125": [0, 0, 0],
						"0.25": [0, 0, 27.5]
					},
					"position": {
						"0.0": [0, 0, 0],
						"0.125": [0, 0, 0],
						"0.25": [0, -0.25, 0]
					},
					"scale": {
						"0.0": [1, 1, 1],
						"0.25": [1.4, 0.2, 1]
					}
				},
				"hair_back": {
					"rotation": {
						"0.0": [-17.5, 0, 0],
						"0.25": [32.5, 0, 0],
						"0.75": [40, 0, 0],
						"1.0": [57.89618, -5.35355, -8.45862],
						"1.5": [73.4061, -6.80364, -13.27092],
						"2.0": [-32.22536, 1.15795, -0.53237]
					},
					"position": {
						"0.0": [0, -1, 1],
						"0.25": [0, -2, -2],
						"1.0": [0, -2, -3],
						"1.5": [0, -3.5, -3.5],
						"2.0": [0, -2, 1.75]
					}
				},
				"hat": {
					"rotation": {
						"0.0": [-4.98107, -0.43523, -4.98107],
						"0.25": [-11.83244, 5.85226, 8.65978],
						"0.75": [-21.83244, 5.85226, 8.65978],
						"1.0": [-62.11421, -4.6106, -16.80914],
						"1.5": [-110.6836, -17.79845, -24.11335],
						"2.0": [-67.6812, -3.04352, -26.86742]
					},
					"position": {
						"0.0": [0, 0, 0],
						"0.25": [0, 0, 0],
						"0.75": [0, 0, 0],
						"1.0": [-2, 7, 6],
						"1.5": [-7, -11, 24],
						"2.0": [-3, -3, 3]
					}
				},
				"legs": {
					"position": {
						"0.0": [0, 0, 0],
						"1.0": [0, -4, -7],
						"1.5": [0, -2, -3]
					}
				},
				"leg_left": {
					"rotation": {
						"0.0": [-4.33151, 30.09432, -0.0055],
						"0.25": [-33.77448, 24.84785, -9.60909],
						"0.75": [33.72552, 24.84785, -9.60909],
						"1.5": [63.72552, 24.84785, -9.60909],
						"2.0": [35.50965, 22.0058, -5.12489]
					},
					"position": [0, 0, 0]
				},
				"leg_right": {
					"rotation": {
						"0.0": [10.98238, -14.3042, -5.20206],
						"0.25": [-1.51762, -14.3042, -5.20206],
						"0.75": [30.98238, -14.3042, -5.20206],
						"1.0": [48.48238, -14.3042, -5.20206],
						"1.5": [73.48238, -14.3042, -5.20206],
						"2.0": [36.8982, -11.33296, -9.32683]
					},
					"position": [0, 0, 0]
				}
			}
		}
	}
}